MANIFEST.in
README.md
requirements.txt
requirements_dev.txt
setup.cfg
setup.py
free_meal_inviter/__init__.py
free_meal_inviter/cli.py
free_meal_inviter.egg-info/PKG-INFO
free_meal_inviter.egg-info/SOURCES.txt
free_meal_inviter.egg-info/dependency_links.txt
free_meal_inviter.egg-info/entry_points.txt
free_meal_inviter.egg-info/requires.txt
free_meal_inviter.egg-info/top_level.txt
free_meal_inviter/app/__init__.py
free_meal_inviter/app/geo.py
free_meal_inviter/app/inviter.py
free_meal_inviter/app/office.py
free_meal_inviter/app/parsers.py
free_meal_inviter/app/person.py
free_meal_inviter/app/services.py