Metadata-Version: 1.1
Name: free-meal-inviter
Version: 0.0.4
Summary: Invite friends around you for a free meal.
Home-page: https://github.com/bertucho/free_meal_inviter
Author: Alberto Egido
Author-email: raise.AlbertoError@gmail.com
License: BSD
Download-URL: https://github.com/bertucho/free_meal_inviter/tarball/0.0.4
Platform: UNKNOWN
Classifier: Development Status :: 3 - Alpha
Classifier: Intended Audience :: Developers
Classifier: Programming Language :: Python :: 3
